tk3d/__init__.py
tk3d/__pycache__/__init__.cpython-39.pyc
tk3d/api/human.py
tk3d/api/open3dapi.py
tk3d/api/pywavfront.py
tk3d/api/vispyapi.py
tk3d/api/__pycache__/human.cpython-39.pyc
tk3d/api/__pycache__/open3dapi.cpython-39.pyc
tk3d/api/__pycache__/pywavfront.cpython-39.pyc
tk3d-0.0.1a1.dist-info/LICENSE
tk3d-0.0.1a1.dist-info/METADATA
tk3d-0.0.1a1.dist-info/WHEEL
tk3d-0.0.1a1.dist-info/top_level.txt
tk3d-0.0.1a1.dist-info/RECORD
