Metadata-Version: 2.1
Name: tk3d
Version: 0.0.1a1
Summary: 3D Modeling Toolkit
Home-page: https://github.com/dhchenx/tk3d
Author: Donghua Chen
Author-email: douglaschan@126.com
License: MIT
Project-URL: Bug Reports, https://github.com/dhchenx/tk3d/issues
Project-URL: Source, https://github.com/dhchenx/tk3d
Keywords: 3d modeling
Platform: UNKNOWN
Classifier: Development Status :: 5 - Production/Stable
Classifier: Intended Audience :: Developers
Classifier: Topic :: Software Development :: Build Tools
Classifier: License :: OSI Approved :: MIT License
Classifier: Programming Language :: Python :: 3
Classifier: Programming Language :: Python :: 3.6
Classifier: Programming Language :: Python :: 3.7
Classifier: Programming Language :: Python :: 3.8
Classifier: Programming Language :: Python :: 3.9
Classifier: Programming Language :: Python :: 3 :: Only
Requires-Python: >=3.6, <4
License-File: LICENSE
Requires-Dist: pywavefront
Provides-Extra: dev
Requires-Dist: check-manifest ; extra == 'dev'
Provides-Extra: test
Requires-Dist: coverage ; extra == 'test'
